hipolita/__init__.py
hipolita/core.py
hipolita/data_recovery/__init__.py
hipolita/data_recovery/adapters/api_adapter.py
hipolita/data_recovery/adapters/ckan_adapter.py
hipolita/data_recovery/interfaces/__init__.py
hipolita/data_recovery/interfaces/adapter.py
hipolita/data_recovery/interfaces/portal.py
hipolita/data_recovery/portals/portal_dados_abertos_br.py
hipolita/data_recovery/portals/portal_data_gov_us.py
hipolita/types.py
hipolita-0.2.2.dist-info/METADATA
hipolita-0.2.2.dist-info/WHEEL
hipolita-0.2.2.dist-info/licenses/LICENSE
hipolita-0.2.2.dist-info/RECORD
