Metadata-Version: 2.4
Name: hipolita
Version: 0.2.2
Summary: This project is an implementation of the Hipolita framework
License: MIT
License-File: LICENSE
Author: Matheus Erthal Amâncio da Silva
Author-email: matheusamancio@id.uff.br
Requires-Python: >=3.10
Classifier: License :: OSI Approved :: MIT License
Classifier: Programming Language :: Python :: 3
Classifier: Programming Language :: Python :: 3.10
Classifier: Programming Language :: Python :: 3.11
Classifier: Programming Language :: Python :: 3.12
Classifier: Programming Language :: Python :: 3.13
Classifier: Programming Language :: Python :: 3.14
Requires-Dist: aiohttp (>=3.13.3,<4.0.0)
Requires-Dist: numpy (>=1.24.0,<2.0.0)
Requires-Dist: pandas (>=2.0.0,<3.0.0)
